cricket_scoring/__init__.py
cricket_scoring/batting.py
cricket_scoring/bowling.py
cricket_scoring/match.py
cricket_scoring/utils.py
cricket_scoring-1.0.1.dist-info/METADATA
cricket_scoring-1.0.1.dist-info/WHEEL
cricket_scoring-1.0.1.dist-info/top_level.txt
cricket_scoring-1.0.1.dist-info/RECORD
